localtranscribe/__init__.py
localtranscribe/api/__init__.py
localtranscribe/api/client.py
localtranscribe/api/types.py
localtranscribe/batch/__init__.py
localtranscribe/batch/processor.py
localtranscribe/cli/__init__.py
localtranscribe/cli/main.py
localtranscribe/cli/commands/__init__.py
localtranscribe/cli/commands/batch.py
localtranscribe/cli/commands/config.py
localtranscribe/cli/commands/doctor.py
localtranscribe/cli/commands/label.py
localtranscribe/cli/commands/process.py
localtranscribe/cli/commands/version.py
localtranscribe/config/__init__.py
localtranscribe/config/defaults.py
localtranscribe/config/loader.py
localtranscribe/core/__init__.py
localtranscribe/core/combination.py
localtranscribe/core/diarization.py
localtranscribe/core/path_resolver.py
localtranscribe/core/transcription.py
localtranscribe/formats/__init__.py
localtranscribe/formats/base.py
localtranscribe/formats/json_format.py
localtranscribe/formats/srt.py
localtranscribe/formats/txt.py
localtranscribe/formats/vtt.py
localtranscribe/health/__init__.py
localtranscribe/health/doctor.py
localtranscribe/labels/__init__.py
localtranscribe/labels/manager.py
localtranscribe/pipeline/__init__.py
localtranscribe/pipeline/orchestrator.py
localtranscribe/utils/__init__.py
localtranscribe/utils/download.py
localtranscribe/utils/errors.py
localtranscribe/utils/file_safety.py
localtranscribe/utils/progress.py
localtranscribe-2.0.2b3.dist-info/licenses/LICENSE
localtranscribe-2.0.2b3.dist-info/METADATA
localtranscribe-2.0.2b3.dist-info/WHEEL
localtranscribe-2.0.2b3.dist-info/entry_points.txt
localtranscribe-2.0.2b3.dist-info/top_level.txt
localtranscribe-2.0.2b3.dist-info/RECORD
