Metadata-Version: 2.4
Name: localtranscribe
Version: 2.0.2b3
Summary: Privacy-first audio transcription with speaker diarization. Entirely offline.
Author: LocalTranscribe Contributors
License: MIT
Project-URL: Homepage, https://github.com/aporb/LocalTranscribe
Project-URL: Repository, https://github.com/aporb/LocalTranscribe
Project-URL: Documentation, https://github.com/aporb/LocalTranscribe/blob/main/README.md
Project-URL: Issues, https://github.com/aporb/LocalTranscribe/issues
Keywords: transcription,diarization,whisper,pyannote,speech-to-text,apple-silicon,cli
Classifier: Development Status :: 4 - Beta
Classifier: Intended Audience :: Developers
Classifier: Intended Audience :: Science/Research
Classifier: License :: OSI Approved :: MIT License
Classifier: Programming Language :: Python :: 3
Classifier: Programming Language :: Python :: 3.9
Classifier: Programming Language :: Python :: 3.10
Classifier: Programming Language :: Python :: 3.11
Classifier: Programming Language :: Python :: 3.12
Classifier: Programming Language :: Python :: 3.13
Classifier: Topic :: Multimedia :: Sound/Audio :: Speech
Classifier: Topic :: Scientific/Engineering :: Artificial Intelligence
Classifier: Environment :: Console
Requires-Python: >=3.9
License-File: LICENSE
Requires-Dist: torch>=2.0.0
Requires-Dist: torchaudio>=2.0.0
Requires-Dist: pyannote-audio>=3.0.0
Requires-Dist: pyannote-core>=6.0.0
Requires-Dist: pyannote-pipeline>=4.0.0
Requires-Dist: typer[all]>=0.9.0
Requires-Dist: rich>=13.0.0
Requires-Dist: pydub>=0.25.1
Requires-Dist: soundfile>=0.12.0
Requires-Dist: librosa>=0.10.0
Requires-Dist: audioread>=3.0.0
Requires-Dist: python-dotenv>=0.19.0
Requires-Dist: pyyaml>=6.0
Requires-Dist: numpy>=1.21.0
Requires-Dist: scipy>=1.7.0
Requires-Dist: huggingface-hub>=0.16.0
Requires-Dist: tqdm>=4.65.0
Provides-Extra: mlx
Requires-Dist: mlx-whisper>=0.1.0; extra == "mlx"
Requires-Dist: mlx>=0.0.10; extra == "mlx"
Provides-Extra: faster
Requires-Dist: faster-whisper>=0.10.0; extra == "faster"
Provides-Extra: original
Requires-Dist: openai-whisper>=20230124; extra == "original"
Provides-Extra: all
Requires-Dist: mlx-whisper>=0.1.0; extra == "all"
Requires-Dist: mlx>=0.0.10; extra == "all"
Requires-Dist: faster-whisper>=0.10.0; extra == "all"
Requires-Dist: openai-whisper>=20230124; extra == "all"
Provides-Extra: dev
Requires-Dist: pytest>=7.4.0; extra == "dev"
Requires-Dist: pytest-cov>=4.1.0; extra == "dev"
Requires-Dist: black>=23.0.0; extra == "dev"
Requires-Dist: mypy>=1.5.0; extra == "dev"
Requires-Dist: ruff>=0.0.290; extra == "dev"
Requires-Dist: pre-commit>=3.3.0; extra == "dev"
Dynamic: license-file
